python_releaser/__init__.py
python_releaser/__main__.py
tests/__init__.py
python_releaser-0.0.1.dist-info/LICENSE
python_releaser-0.0.1.dist-info/METADATA
python_releaser-0.0.1.dist-info/WHEEL
python_releaser-0.0.1.dist-info/entry_points.txt
python_releaser-0.0.1.dist-info/top_level.txt
python_releaser-0.0.1.dist-info/RECORD
